Metadata-Version: 1.0
Name: fakechain
Version: 0.0.0a1
Summary: Planned project for a naive DLT implementation for prototyping and education purposes
Home-page: UNKNOWN
Author: UNKNOWN
Author-email: UNKNOWN
License: UNKNOWN
Platform: UNKNOWN
